vsmstreamer/__init__.py
vsmstreamer-0.2.0.dist-info/LICENSE
vsmstreamer-0.2.0.dist-info/METADATA
vsmstreamer-0.2.0.dist-info/WHEEL
vsmstreamer-0.2.0.dist-info/entry_points.txt
vsmstreamer-0.2.0.dist-info/top_level.txt
vsmstreamer-0.2.0.dist-info/RECORD
