Metadata-Version: 2.1
Name: vsmstreamer
Version: 0.2.0
Summary: Cisco Video Surveillance Manager Streamer
Home-page: https://github.com/kprav33n/vsmstreamer
Author: Praveen Kumar
Author-email: praveen+pypi@kumar.in
License: UNKNOWN
Platform: UNKNOWN
Classifier: Development Status :: 3 - Alpha
Classifier: Programming Language :: Python :: 3
Classifier: Programming Language :: Python :: 2.7
Classifier: Operating System :: MacOS
Classifier: License :: OSI Approved :: MIT License
Requires-Dist: PyCocoa
Requires-Dist: configparser
Requires-Dist: python-vlc
Requires-Dist: requests
